doe_box/__init__.py
doe_box/bbdesign.py
doe_box/ccdesign.py
doe_box/fracfact.py
doe_box/fracfactgen.py
doe_box/fullfact.py
doe_box/lhs.py
doe_box/parser.py
doe_toolbox-1.3.dist-info/LICENSE
doe_toolbox-1.3.dist-info/METADATA
doe_toolbox-1.3.dist-info/WHEEL
doe_toolbox-1.3.dist-info/top_level.txt
doe_toolbox-1.3.dist-info/RECORD
